to_cei/charter.py
to_cei/charter_group.py
to_cei/config.py
to_cei/filecache.py
to_cei/helpers.py
to_cei/seal.py
to_cei/validator.py
to_cei/xml_assembler.py
to_cei-0.3.1.dist-info/licenses/LICENSE
to_cei-0.3.1.dist-info/METADATA
to_cei-0.3.1.dist-info/WHEEL
to_cei-0.3.1.dist-info/top_level.txt
to_cei-0.3.1.dist-info/RECORD
