Metadata-Version: 2.4
Name: to_cei
Version: 0.3.1
Summary: to-CEI
Home-page: https://github.com/icaruseu/to-cei
Author: Daniel Jeller
Author-email: it@icar-us.eu
License: GPL 3.0
Classifier: Intended Audience :: Developers
Classifier: License :: OSI Approved :: GNU Lesser General Public License v3 (LGPLv3)
Classifier: Programming Language :: Python
Classifier: Programming Language :: Python :: 3
Classifier: Programming Language :: Python :: 3.10
Classifier: Operating System :: OS Independent
License-File: LICENSE
Requires-Dist: astropy
Requires-Dist: lxml
Requires-Dist: requests
Requires-Dist: xmlschema
Dynamic: author
Dynamic: author-email
Dynamic: classifier
Dynamic: description
Dynamic: description-content-type
Dynamic: home-page
Dynamic: license
Dynamic: license-file
Dynamic: requires-dist
Dynamic: summary
